qmicroscope/__init__.py
qmicroscope/_version.py
qmicroscope/container.py
qmicroscope/microscope.py
qmicroscope/plugin_settings.py
qmicroscope/settings.py
qmicroscope/plugins/__init__.py
qmicroscope/plugins/base_plugin.py
qmicroscope/plugins/c2c_plugin.py
qmicroscope/plugins/crosshair_plugin.py
qmicroscope/plugins/grid_plugin.py
qmicroscope/plugins/mousewheel_camera_zoom.py
qmicroscope/plugins/preset_plugin.py
qmicroscope/plugins/record_plugin.py
qmicroscope/plugins/scale_plugin.py
qmicroscope/plugins/square_grid.py
qmicroscope/plugins/toggle_plugin.py
qmicroscope/plugins/vector_plugin.py
qmicroscope/plugins/zoom_plugin.py
qmicroscope/utils/__init__.py
qmicroscope/utils/recorder.py
qmicroscope/utils/settings.py
qmicroscope/widgets/color_button.py
qmicroscope/widgets/downloader.py
qmicroscope/widgets/rubberband.py
qmicroscope-0.0.5.dist-info/METADATA
qmicroscope-0.0.5.dist-info/WHEEL
qmicroscope-0.0.5.dist-info/licenses/LICENSE
qmicroscope-0.0.5.dist-info/RECORD
