Metadata-Version: 2.1
Name: qmicroscope
Version: 0.0.5
Summary: A camera widget for qt GUIs using qtpy
Author-email: "Venkateswaran (Shekar) Shekar" <vshekar1@bnl.gov>
License-File: LICENSE
Classifier: Development Status :: 4 - Beta
Classifier: Programming Language :: Python :: 3 :: Only
Classifier: Programming Language :: Python :: 3.8
Classifier: Programming Language :: Python :: 3.9
Classifier: Programming Language :: Python :: 3.10
Classifier: Programming Language :: Python :: 3.11
Classifier: Programming Language :: Python :: 3.12
Classifier: Topic :: Scientific/Engineering :: Physics
Requires-Python: >=3.8
Requires-Dist: opencv-python
Requires-Dist: pillow
Requires-Dist: qtpy
